{"is_source_file": true, "format": "JavaScript", "description": "Test setup file for configuring custom jest matchers for DOM assertions using '@testing-library/jest-dom'.", "external_files": ["@testing-library/jest-dom"], "external_methods": ["expect", "toHaveTextContent"], "published": [], "classes": [], "methods": [], "calls": ["expect", "toHaveTextContent"], "search-terms": ["setupTests.js", "jest-dom", "testing-library", "test setup", "custom matchers"], "state": 2, "file_id": 9, "knowledge_revision": 23, "git_revision": "d70ab0ab1652eeba7f0ebd6020f78b1336d370c6", "ctags": [], "hash": "1a77571e1a8cf36018a41bcedf60db75", "format-version": 4, "code-base-name": "notes_frontend", "filename": "notes_frontend/src/setupTests.js", "revision_history": [{"23": "d70ab0ab1652eeba7f0ebd6020f78b1336d370c6"}]}